pyScannerWrapper/__init__.py
pyScannerWrapper/core/_BaseScanner.py
pyScannerWrapper/core/__init__.py
pyScannerWrapper/exceptions/_ScannerNotFoundException.py
pyScannerWrapper/exceptions/__init__.py
pyScannerWrapper/scanners/_Masscan.py
pyScannerWrapper/scanners/__init__.py
pyScannerWrapper/structs/_ScanResults.py
pyScannerWrapper/structs/_ServerResult.py
pyScannerWrapper/structs/__init__.py
pyScannerWrapper-0.2.1.dist-info/LICENSE.txt
pyScannerWrapper-0.2.1.dist-info/METADATA
pyScannerWrapper-0.2.1.dist-info/WHEEL
pyScannerWrapper-0.2.1.dist-info/top_level.txt
pyScannerWrapper-0.2.1.dist-info/RECORD
