Metadata-Version: 2.1
Name: pyScannerWrapper
Version: 0.2.1
Summary: Easy-to-use Python wrapper for various port scanners.
Home-page: https://github.com/Oreeeee/pyScannerWrapper
Author: Oreeeee
License: MIT
Classifier: Development Status :: 4 - Beta
Classifier: Intended Audience :: Developers
Classifier: License :: OSI Approved :: MIT License
Classifier: Operating System :: OS Independent
Classifier: Programming Language :: Python :: 3.8
Classifier: Programming Language :: Python :: 3.9
Classifier: Programming Language :: Python :: 3.10
Classifier: Programming Language :: Python :: 3.11
Classifier: Topic :: Software Development :: Libraries
Classifier: Topic :: Software Development :: Libraries :: Python Modules
License-File: LICENSE.txt
